[{"catNum": "LOC1352", "audioUrls": []}, {"catNum": "LOC1353", "audioUrls": []}, {"catNum": "LOC1354", "audioUrls": []}, {"catNum": "LOC1355", "audioUrls": []}, {"catNum": "LOC1356", "audioUrls": []}, {"catNum": "LOC1357", "audioUrls": []}, {"catNum": "LOC1358", "audioUrls": []}, {"catNum": "LOC1359", "audioUrls": []}, {"catNum": "LOC136", "audioUrls": []}, {"catNum": "LOC1360", "audioUrls": []}, {"catNum": "LOC1361", "audioUrls": []}, {"catNum": "LOC1362", "audioUrls": []}, {"catNum": "LOC1363", "audioUrls": []}, {"catNum": "LOC1364", "audioUrls": []}, {"catNum": "LOC1365", "audioUrls": []}, {"catNum": "LOC1366", "audioUrls": []}, {"catNum": "LOC1367", "audioUrls": []}, {"catNum": "LOC1368", "audioUrls": []}, {"catNum": "LOC1369", "audioUrls": []}, {"catNum": "LOC137", "audioUrls": []}, {"catNum": "LOC1370", "audioUrls": []}, {"catNum": "LOC1371", "audioUrls": []}, {"catNum": "LOC1372", "audioUrls": []}, {"catNum": "LOC1373", "audioUrls": []}, {"catNum": "LOC1374", "audioUrls": []}, {"catNum": "LOC1375", "audioUrls": []}, {"catNum": "LOC1376", "audioUrls": []}, {"catNum": "LOC1377", "audioUrls": []}, {"catNum": "LOC1378", "audioUrls": []}, {"catNum": "LOC1379", "audioUrls": []}, {"catNum": "LOC138", "audioUrls": []}, {"catNum": "LOC1380", "audioUrls": []}, {"catNum": "LOC1381", "audioUrls": []}, {"catNum": "LOC1382", "audioUrls": []}, {"catNum": "LOC1383", "audioUrls": []}, {"catNum": "LOC1384", "audioUrls": []}, {"catNum": "LOC1385", "audioUrls": []}, {"catNum": "LOC1386", "audioUrls": []}, {"catNum": "LOC1387", "audioUrls": []}, {"catNum": "LOC1388", "audioUrls": []}, {"catNum": "LOC1389", "audioUrls": []}, {"catNum": "LOC139", "audioUrls": []}, {"catNum": "LOC1390", "audioUrls": []}, {"catNum": "LOC1391", "audioUrls": []}, {"catNum": "LOC1392", "audioUrls": []}, {"catNum": "LOC1393", "audioUrls": []}, {"catNum": "LOC1394", "audioUrls": []}, {"catNum": "LOC1395", "audioUrls": []}, {"catNum": "LOC1396", "audioUrls": []}, {"catNum": "LOC1397", "audioUrls": []}, {"catNum": "LOC1398", "audioUrls": []}, {"catNum": "LOC1399", "audioUrls": []}, {"catNum": "LOC14", "audioUrls": []}, {"catNum": "LOC140", "audioUrls": []}, {"catNum": "LOC1400", "audioUrls": []}, {"catNum": "LOC1401", "audioUrls": []}, {"catNum": "LOC1402", "audioUrls": []}, {"catNum": "LOC1403", "audioUrls": []}, {"catNum": "LOC1404", "audioUrls": []}, {"catNum": "LOC1405", "audioUrls": []}, {"catNum": "LOC1406", "audioUrls": []}, {"catNum": "LOC1407", "audioUrls": []}, {"catNum": "LOC1408", "audioUrls": []}, {"catNum": "LOC1409", "audioUrls": []}, {"catNum": "LOC141", "audioUrls": []}, {"catNum": "LOC1410", "audioUrls": []}, {"catNum": "LOC1411", "audioUrls": []}, {"catNum": "LOC1412", "audioUrls": []}, {"catNum": "LOC1413", "audioUrls": []}, {"catNum": "LOC1415", "audioUrls": []}, {"catNum": "LOC1419", "audioUrls": []}, {"catNum": "LOC142", "audioUrls": []}, {"catNum": "LOC1421", "audioUrls": []}, {"catNum": "LOC1422", "audioUrls": []}, {"catNum": "LOC1423", "audioUrls": []}, {"catNum": "LOC1424", "audioUrls": []}, {"catNum": "LOC1425", "audioUrls": []}, {"catNum": "LOC1426", "audioUrls": []}, {"catNum": "LOC1427", "audioUrls": []}, {"catNum": "LOC1428", "audioUrls": []}, {"catNum": "LOC1429", "audioUrls": []}, {"catNum": "LOC143", "audioUrls": []}, {"catNum": "LOC1430", "audioUrls": []}, {"catNum": "LOC1431", "audioUrls": []}, {"catNum": "LOC1432", "audioUrls": []}, {"catNum": "LOC1433", "audioUrls": []}, {"catNum": "LOC1434", "audioUrls": []}, {"catNum": "LOC1441", "audioUrls": []}, {"catNum": "LOC1442", "audioUrls": []}, {"catNum": "LOC1443", "audioUrls": []}, {"catNum": "LOC1444", "audioUrls": []}, {"catNum": "LOC1445", "audioUrls": []}, {"catNum": "LOC1446", "audioUrls": []}, {"catNum": "LOC1447", "audioUrls": []}, {"catNum": "LOC1448", "audioUrls": []}, {"catNum": "LOC1449", "audioUrls": []}, {"catNum": "LOC145", "audioUrls": []}, {"catNum": "LOC1450", "audioUrls": []}, {"catNum": "LOC1451", "audioUrls": []}, {"catNum": "LOC1452", "audioUrls": []}, {"catNum": "LOC1455", "audioUrls": []}, {"catNum": "LOC1456", "audioUrls": []}, {"catNum": "LOC1457", "audioUrls": []}, {"catNum": "LOC1458", "audioUrls": []}, {"catNum": "LOC1459", "audioUrls": []}, {"catNum": "LOC1460", "audioUrls": []}, {"catNum": "LOC1467", "audioUrls": []}, {"catNum": "LOC1468", "audioUrls": []}, {"catNum": "LOC1469", "audioUrls": []}, {"catNum": "LOC1470", "audioUrls": []}, {"catNum": "LOC1471", "audioUrls": []}, {"catNum": "LOC1472", "audioUrls": []}, {"catNum": "LOC1473", "audioUrls": []}, {"catNum": "LOC1474", "audioUrls": []}, {"catNum": "LOC1475", "audioUrls": []}, {"catNum": "LOC1476", "audioUrls": []}, {"catNum": "LOC1477", "audioUrls": []}, {"catNum": "LOC1478", "audioUrls": []}, {"catNum": "LOC1479", "audioUrls": []}, {"catNum": "LOC148", "audioUrls": []}, {"catNum": "LOC1480", "audioUrls": []}, {"catNum": "LOC1481", "audioUrls": []}, {"catNum": "LOC1482", "audioUrls": []}, {"catNum": "LOC1483", "audioUrls": []}, {"catNum": "LOC1484", "audioUrls": []}, {"catNum": "LOC1485", "audioUrls": []}, {"catNum": "LOC1486", "audioUrls": []}, {"catNum": "LOC1487", "audioUrls": []}, {"catNum": "LOC1488", "audioUrls": []}, {"catNum": "LOC1489", "audioUrls": []}, {"catNum": "LOC1490", "audioUrls": []}, {"catNum": "LOC1491", "audioUrls": []}, {"catNum": "LOC1492", "audioUrls": []}, {"catNum": "LOC1493", "audioUrls": []}, {"catNum": "LOC1494", "audioUrls": []}, {"catNum": "LOC1495", "audioUrls": []}, {"catNum": "LOC1496", "audioUrls": []}, {"catNum": "LOC1497", "audioUrls": []}, {"catNum": "LOC15", "audioUrls": []}, {"catNum": "LOC1503", "audioUrls": []}, {"catNum": "LOC1504", "audioUrls": []}, {"catNum": "LOC151", "audioUrls": []}, {"catNum": "LOC1512", "audioUrls": []}, {"catNum": "LOC1513", "audioUrls": []}, {"catNum": "LOC1514", "audioUrls": []}, {"catNum": "LOC1515", "audioUrls": []}, {"catNum": "LOC1516", "audioUrls": []}, {"catNum": "LOC1517", "audioUrls": []}, {"catNum": "LOC1518", "audioUrls": []}, {"catNum": "LOC1519", "audioUrls": []}, {"catNum": "LOC152", "audioUrls": []}, {"catNum": "LOC1520", "audioUrls": []}, {"catNum": "LOC1521", "audioUrls": []}, {"catNum": "LOC1522", "audioUrls": []}, {"catNum": "LOC1523", "audioUrls": []}, {"catNum": "LOC1524", "audioUrls": []}, {"catNum": "LOC1525", "audioUrls": []}, {"catNum": "LOC1526", "audioUrls": []}, {"catNum": "LOC1527", "audioUrls": []}, {"catNum": "LOC1528", "audioUrls": []}, {"catNum": "LOC1529", "audioUrls": []}, {"catNum": "LOC153", "audioUrls": []}, {"catNum": "LOC1530", "audioUrls": []}, {"catNum": "LOC1531", "audioUrls": []}, {"catNum": "LOC1532", "audioUrls": []}, {"catNum": "LOC1533", "audioUrls": []}, {"catNum": "LOC1534", "audioUrls": []}]